pydantic_argparse_next/__init__.py
pydantic_argparse_next/parser/__init__.py
pydantic_argparse_next/parser/classes.py
pydantic_argparse_next/parser/fields.py
pydantic_argparse_next/parser/parse.py
pydantic_argparse_next/parser/parser.py
pydantic_argparse_next/parser/utils.py
pydantic_argparse_next-1.0.7.dist-info/METADATA
pydantic_argparse_next-1.0.7.dist-info/WHEEL
pydantic_argparse_next-1.0.7.dist-info/RECORD
