Metadata-Version: 2.3
Name: pydantic-argparse-next
Version: 1.0.7
Summary: Pydantic 2 argparse.
Keywords: pydantic,argparse,parser,argparser,cli
Author: oevergodofchaos
Author-email: vezonzzzzzz@gmail.com
Requires-Python: >=3.11
Classifier: Programming Language :: Python :: 3
Classifier: Programming Language :: Python :: 3.11
Classifier: Programming Language :: Python :: 3.12
Classifier: Programming Language :: Python :: 3.13
Requires-Dist: pydantic (>=2.11.3,<3.0.0)
Requires-Dist: rich (>=14.0.0,<15.0.0)
Project-URL: Documentation, https://github.com/overgodofchaos/pydantic-argparse-next
Project-URL: Homepage, https://github.com/overgodofchaos/pydantic-argparse-next
Project-URL: Repository, https://github.com/overgodofchaos/pydantic-argparse-next
